odoo10_addon_sale_manual_delivery-10.0.2.0.1-py3.8-nspkg.pth
odoo/addons/sale_manual_delivery/README.rst
odoo/addons/sale_manual_delivery/__init__.py
odoo/addons/sale_manual_delivery/__manifest__.py
odoo/addons/sale_manual_delivery/i18n/sale_manual_delivery.pot
odoo/addons/sale_manual_delivery/models/__init__.py
odoo/addons/sale_manual_delivery/models/crm_team.py
odoo/addons/sale_manual_delivery/models/procurement.py
odoo/addons/sale_manual_delivery/models/sale_order.py
odoo/addons/sale_manual_delivery/models/sale_order_line.py
odoo/addons/sale_manual_delivery/models/stock_move.py
odoo/addons/sale_manual_delivery/static/description/icon.png
odoo/addons/sale_manual_delivery/static/description/icon.svg
odoo/addons/sale_manual_delivery/tests/__init__.py
odoo/addons/sale_manual_delivery/tests/test_manual_delivery.py
odoo/addons/sale_manual_delivery/views/crm_team_view.xml
odoo/addons/sale_manual_delivery/views/procurement_view.xml
odoo/addons/sale_manual_delivery/views/sale_order_view.xml
odoo/addons/sale_manual_delivery/wizard/__init__.py
odoo/addons/sale_manual_delivery/wizard/line.py
odoo/addons/sale_manual_delivery/wizard/manual_proc.py
odoo/addons/sale_manual_delivery/wizard/manual_proc_view.xml
odoo10_addon_sale_manual_delivery-10.0.2.0.1.dist-info/METADATA
odoo10_addon_sale_manual_delivery-10.0.2.0.1.dist-info/WHEEL
odoo10_addon_sale_manual_delivery-10.0.2.0.1.dist-info/namespace_packages.txt
odoo10_addon_sale_manual_delivery-10.0.2.0.1.dist-info/top_level.txt
odoo10_addon_sale_manual_delivery-10.0.2.0.1.dist-info/RECORD
