Metadata-Version: 2.1
Name: odoo10-addon-sale-manual-delivery
Version: 10.0.2.0.1
Summary: Create manually your deliveries
Home-page: https://github.com/OCA/sale-workflow
Author: Camptocamp SA, Odoo Community Association (OCA)
Author-email: support@odoo-community.org
License: AGPL-3
Platform: UNKNOWN
Classifier: Programming Language :: Python
Classifier: Framework :: Odoo
Classifier: Framework :: Odoo :: 10.0
Classifier: License :: OSI Approved :: GNU Affero General Public License v3
Requires-Python: ~=2.7
Requires-Dist: odoo (<10.1dev,>=10.0)
